rekuest_next/__init__.py
rekuest_next/annotations.py
rekuest_next/app.py
rekuest_next/arkitekt.py
rekuest_next/coercible_types.py
rekuest_next/declare.py
rekuest_next/errors.py
rekuest_next/funcs.py
rekuest_next/helpers.py
rekuest_next/messages.py
rekuest_next/protocols.py
rekuest_next/py.typed
rekuest_next/rath.py
rekuest_next/register.py
rekuest_next/rekuest.py
rekuest_next/remote.py
rekuest_next/scalars.py
rekuest_next/structure.py
rekuest_next/widgets.py
rekuest_next/actors/__init__.py
rekuest_next/actors/actify.py
rekuest_next/actors/base.py
rekuest_next/actors/context.py
rekuest_next/actors/debug.py
rekuest_next/actors/errors.py
rekuest_next/actors/functional.py
rekuest_next/actors/helper.py
rekuest_next/actors/sync.py
rekuest_next/actors/types.py
rekuest_next/actors/vars.py
rekuest_next/agents/__init__.py
rekuest_next/agents/base.py
rekuest_next/agents/context.py
rekuest_next/agents/errors.py
rekuest_next/agents/extension.py
rekuest_next/agents/lock.py
rekuest_next/agents/registry.py
rekuest_next/agents/extensions/default.py
rekuest_next/agents/hooks/__init__.py
rekuest_next/agents/hooks/background.py
rekuest_next/agents/hooks/errors.py
rekuest_next/agents/hooks/registry.py
rekuest_next/agents/hooks/startup.py
rekuest_next/agents/transport/__init__.py
rekuest_next/agents/transport/base.py
rekuest_next/agents/transport/errors.py
rekuest_next/agents/transport/test_transport.py
rekuest_next/agents/transport/types.py
rekuest_next/agents/transport/websocket.py
rekuest_next/api/__init__.py
rekuest_next/api/project.json
rekuest_next/api/schema.graphql
rekuest_next/api/schema.py
rekuest_next/contrib/__init__.py
rekuest_next/contrib/arkitekt/websocket_agent_transport.py
rekuest_next/contrib/fastapi/__init__.py
rekuest_next/contrib/fastapi/agent.py
rekuest_next/contrib/fastapi/routes.py
rekuest_next/contrib/fastapi/testing.py
rekuest_next/contrib/rath/set_assignation_link.py
rekuest_next/definition/__init__.py
rekuest_next/definition/define.py
rekuest_next-0.32.1.dist-info/METADATA
rekuest_next-0.32.1.dist-info/WHEEL
rekuest_next-0.32.1.dist-info/RECORD
