Metadata-Version: 2.4
Name: rekuest-next
Version: 0.32.1
Summary: rpc and node backbone
Author-email: jhnnsrs <jhnnsrs@gmail.com>
License-Expression: GPL-3.0-or-later
Requires-Python: <4.0,>=3.11
Requires-Dist: docstring-parser>=0.11
Requires-Dist: dokker>=2.2
Requires-Dist: fieldz>=0.0.2
Requires-Dist: inflection>=0.5.1
Requires-Dist: jsonpatch>=1.33
Requires-Dist: koil>=2.4.0
Requires-Dist: pydantic>=2
Requires-Dist: rath>=3.5.1
Requires-Dist: websockets>=12.0
Provides-Extra: types
Requires-Dist: annotated-types>=0.5.0; extra == 'types'
